qtui/__init__.py
qtui/py.typed
qtui/FluentUI/__init__.py
qtui/FluentUI/plugins.qmltypes
qtui/FluentUI/qmldir
qtui/FluentUI/resource.qrc
qtui/FluentUI/resource_rc.py
qtui/FluentUI/runner.py
qtui/FluentUI/utils.py
qtui/FluentUI/Controls/FluAcrylic.qml
qtui/FluentUI/Controls/FluAppBar.qml
qtui/FluentUI/Controls/FluAutoSuggestBox.qml
qtui/FluentUI/Controls/FluBadge.qml
qtui/FluentUI/Controls/FluBreadcrumbBar.qml
qtui/FluentUI/Controls/FluButton.qml
qtui/FluentUI/Controls/FluCalendarPicker.qml
qtui/FluentUI/Controls/FluCarousel.qml
qtui/FluentUI/Controls/FluChart.qml
qtui/FluentUI/Controls/FluCheckBox.qml
qtui/FluentUI/Controls/FluClip.qml
qtui/FluentUI/Controls/FluColorPicker.qml
qtui/FluentUI/Controls/FluComboBox.qml
qtui/FluentUI/Controls/FluContentDialog.qml
qtui/FluentUI/Controls/FluContentPage.qml
qtui/FluentUI/Controls/FluControl.qml
qtui/FluentUI/Controls/FluControlBackground.qml
qtui/FluentUI/Controls/FluCopyableText.qml
qtui/FluentUI/Controls/FluDatePicker.qml
qtui/FluentUI/Controls/FluDivider.qml
qtui/FluentUI/Controls/FluDropDownButton.qml
qtui/FluentUI/Controls/FluEvent.qml
qtui/FluentUI/Controls/FluEventBus.qml
qtui/FluentUI/Controls/FluExpander.qml
qtui/FluentUI/Controls/FluFilledButton.qml
qtui/FluentUI/Controls/FluFlipView.qml
qtui/FluentUI/Controls/FluFocusRectangle.qml
qtui/FluentUI/Controls/FluFrame.qml
qtui/FluentUI/Controls/FluGroupBox.qml
qtui/FluentUI/Controls/FluIcon.qml
qtui/FluentUI/Controls/FluIconButton.qml
qtui/FluentUI/Controls/FluImage.qml
qtui/FluentUI/Controls/FluImageButton.qml
qtui/FluentUI/Controls/FluInfoBar.qml
qtui/FluentUI/Controls/FluItemDelegate.qml
qtui/FluentUI/Controls/FluLauncher.qml
qtui/FluentUI/Controls/FluLoader.qml
qtui/FluentUI/Controls/FluLoadingButton.qml
qtui/FluentUI/Controls/FluMenu.qml
qtui/FluentUI/Controls/FluMenuBar.qml
qtui/FluentUI/Controls/FluMenuBarItem.qml
qtui/FluentUI/Controls/FluMenuItem.qml
qtui/FluentUI/Controls/FluMenuSeparator.qml
qtui/FluentUI/Controls/FluMultilineTextBox.qml
qtui-0.2.0.dist-info/METADATA
qtui-0.2.0.dist-info/WHEEL
qtui-0.2.0.dist-info/licenses/LICENSE
qtui-0.2.0.dist-info/RECORD
