Metadata-Version: 2.4
Name: qtui
Version: 0.2.0
Summary: A collection of UI libraries for pyside6
Author-email: moreih29 <moreih29@gmail.com>
License-File: LICENSE
Requires-Python: >=3.11
Requires-Dist: pillow>=11.0.0
Requires-Dist: pyside6>=6.7.0
Requires-Dist: qasync>=0.27.1
Requires-Dist: qrcode~=7.4.2
